README.md
setup.py
rasa_composite_entities/__init__.py
rasa_composite_entities/composite_entity_extractor.py
rasa_composite_entities.egg-info/PKG-INFO
rasa_composite_entities.egg-info/SOURCES.txt
rasa_composite_entities.egg-info/dependency_links.txt
rasa_composite_entities.egg-info/top_level.txt