Metadata-Version: 2.1
Name: rasa-composite-entities
Version: 0.4.2
Summary: A Rasa NLU component for composite entities
Home-page: https://github.com/BeWe11/rasa_composite_entities
Author: Benjamin Weigang
Author-email: Benjamin.Weigang@mailbox.org
License: UNKNOWN
Platform: UNKNOWN
Classifier: Programming Language :: Python :: 2.7
Classifier: Programming Language :: Python :: 3
Classifier: Programming Language :: Python :: 3.5
Classifier: Programming Language :: Python :: 3.6
Classifier: Programming Language :: Python :: 3.7
Classifier: License :: OSI Approved :: MIT License
Classifier: Operating System :: OS Independent
